chibi_marshmallow/__init__.py
chibi_marshmallow/fields.py
chibi_marshmallow-0.0.1.dist-info/AUTHORS.rst
chibi_marshmallow-0.0.1.dist-info/LICENSE
chibi_marshmallow-0.0.1.dist-info/METADATA
chibi_marshmallow-0.0.1.dist-info/WHEEL
chibi_marshmallow-0.0.1.dist-info/top_level.txt
chibi_marshmallow-0.0.1.dist-info/RECORD
