Metadata-Version: 2.1
Name: chibi-marshmallow
Version: 0.0.1
Summary: fields and snippets for marshmallow
Home-page: https://github.com/dem4ply/chibi_marshmallow
Author: dem4ply
Author-email: dem4ply@gmail.com
License: WTFPL
Keywords: chibi_marshmallow
Classifier: Development Status :: 2 - Pre-Alpha
Classifier: Intended Audience :: Developers
Classifier: License :: Public Domain
Classifier: Natural Language :: English
Classifier: Programming Language :: Python :: 3.7
Classifier: Programming Language :: Python :: 3.8
License-File: LICENSE
License-File: AUTHORS.rst
Requires-Dist: marshmallow (>=3.5.1)
